shard_cli/__init__.py
shard_cli/__main__.py
shard_cli/commands.py
shard_cli/config.py
shard_cli/utils.py
shard_cli-0.1.2.dist-info/entry_points.txt
shard_cli-0.1.2.dist-info/licenses/LICENSE
shard_cli-0.1.2.dist-info/WHEEL
shard_cli-0.1.2.dist-info/METADATA
shard_cli-0.1.2.dist-info/RECORD
