Metadata-Version: 2.4
Name: shard-cli
Version: 0.1.2
Summary: A CLI note-taking tool inspired by Zettelkasten
Author-email: WolfQuery <foxtailoromis@gmail.com>
Requires-Python: >=3.8
License-File: LICENSE
Requires-Dist: typer
Requires-Dist: platformdirs
Requires-Dist: toml
